[
    {
        "path":"",
        "name":"index",
    },
    {
        "path":"index",
        "name":"index",
    },
    {
        "path":"buttons",
        "name":"buttons",
    },
    {
        "path":"cards",
        "name":"cards",
    },
    {
        "path":"utilities-color",
        "name":"utilities-color",
    },
    {
        "path":"utilities-border",
        "name":"utilities-border",
    },
    {
        "path":"utilities-animation",
        "name":"utilities-animation",
    },
    {
        "path":"utilities-other",
        "name":"utilities-other",
    },
    {
        "path":"login",
        "name":"login",
    },
    {
        "path":"register",
        "name":"register",
    },
    {
        "path":"forgot-password",
        "name":"forgot-password",
    },
    {
        "path":"404",
        "name":"404",
    },
    {
        "path":"blank",
        "name":"blank",
    },
    {
        "path":"charts",
        "name":"charts",
    },
    {
        "path":"tables",
        "name":"tables",
    }
]

